README.md
setup.cfg
setup.py
distros_probability/Binomialdistribution.py
distros_probability/Gaussiandistribution.py
distros_probability/Generaldistribution.py
distros_probability/__init__.py
distros_probability.egg-info/PKG-INFO
distros_probability.egg-info/SOURCES.txt
distros_probability.egg-info/dependency_links.txt
distros_probability.egg-info/not-zip-safe
distros_probability.egg-info/top_level.txt