Metadata-Version: 2.1
Name: distros-probability
Version: 0.1
Summary: Gaussian and Binomial distributions
Author: Ataliba Miguel
Author-email: a.miguel@rgu.ac.uk
License: MIT
